getsize.py
getsize-1.1.11.dist-info/LICENSE
getsize-1.1.11.dist-info/METADATA
getsize-1.1.11.dist-info/WHEEL
getsize-1.1.11.dist-info/entry_points.txt
getsize-1.1.11.dist-info/top_level.txt
getsize-1.1.11.dist-info/RECORD
