Metadata-Version: 2.1
Name: getsize
Version: 1.1.11
Summary: Get and display the size of file and directory with binary prefixes
Home-page: https://github.com/JeXLiN/getsize
Author: Sergey Barskov
Author-email: sergeybarskov@gmail.com
License: MIT
Platform: UNKNOWN
Classifier: Development Status :: 5 - Production/Stable
Classifier: Environment :: Console
Classifier: Intended Audience :: Developers
Classifier: Intended Audience :: End Users/Desktop
Classifier: License :: OSI Approved :: MIT License
Classifier: Operating System :: OS Independent
Classifier: Programming Language :: Python :: 3
Classifier: Topic :: Software Development :: Libraries :: Python Modules
Classifier: Topic :: Utilities
